Workbook
Name Slicer_brand: #N/A
Name Slicer_category: #N/A
Name Slicer_customer_segment: #N/A
Name Slicer_payment_method: #N/A

Sheet orders
A1: order_id | B1: customer_id | C1: order_date | D1: order_total | E1: payment_method
A2: 1961864118 | B2: 30065862 | C2: 45490.357 | D2: 3197.07 | E2: Cash
A3: 1549769649 | B3: 9573071 | C3: 45440.551 | D3: 976.55 | E3: Cash
A4: 9185164487 | B4: 45477575 | C4: 45558.547 | D4: 839.05 | E4: UPI
A5: 9644738826 | B5: 88067569 | C5: 45254.678 | D5: 440.23 | E5: Card
A6: 5427684290 | B6: 83298567 | C6: 45250.208 | D6: 2526.68 | E6: Cash
A7: 3265154092 | B7: 43367112 | C7: 45003.687 | D7: 3161.43 | E7: UPI
A8: 4898355547 | B8: 13284996 | C8: 45032.785 | D8: 956.4 | E8: Card
A9: 6568151549 | B9: 88866835 | C9: 45382.268 | D9: 905.47 | E9: Cash
A10: 6006693867 | B10: 24496983 | C10: 45120.992 | D10: 1371.17 | E10: Card
A11: 374186990 | B11: 52215833 | C11: 45147.053 | D11: 1601.19 | E11: Wallet
A12: 4455336265 | B12: 43431724 | C12: 45168.817 | D12: 2362.33 | E12: UPI
A13: 3539286337 | B13: 77559557 | C13: 45041.856 | D13: 1463.8 | E13: Wallet
... A5001: 2494813730 | B5001: 28663279 | C5001: 45161.503 | D5001: 1879.46 | E5001: Card

Sheet order items
A1: order_id | B1: product_id | C1: quantity | D1: unit_price
A2: 1961864118 | B2: 642612 | C2: 3 | D2: 517.03
A3: 1549769649 | B3: 378676 | C3: 1 | D3: 881.42
A4: 9185164487 | B4: 741341 | C4: 2 | D4: 923.84
A5: 9644738826 | B5: 561860 | C5: 1 | D5: 874.78
A6: 5427684290 | B6: 602241 | C6: 2 | D6: 976.55
A7: 3265154092 | B7: 681063 | C7: 1 | D7: 321.28
A8: 4898355547 | B8: 56589 | C8: 3 | D8: 517.77
A9: 6568151549 | B9: 500739 | C9: 2 | D9: 359.98
A10: 6006693867 | B10: 490939 | C10: 1 | D10: 80.25
A11: 374186990 | B11: 760828 | C11: 2 | D11: 563.45
A12: 4455336265 | B12: 753354 | C12: 3 | D12: 423.56
A13: 3539286337 | B13: 684939 | C13: 1 | D13: 727.95
... A5001: 2494813730 | B5001: 136533 | C5001: 1 | D5001: 826.21

Sheet products
A1: product_id | B1: product_name | C1: category | D1: brand | E1: price
A2: 153019 | B2: Onions | C2: Fruits & Vegetables | D2: Aurora LLC | E2: 947.95
A3: 11422 | B3: Potatoes | C3: Fruits & Vegetables | D3: Ramaswamy-Tata | E3: 127.16
A4: 669378 | B4: Potatoes | C4: Fruits & Vegetables | D4: Chadha and Sons | E4: 212.14
A5: 848226 | B5: Tomatoes | C5: Fruits & Vegetables | D5: Barad and Sons | E5: 209.59
A6: 890623 | B6: Onions | C6: Fruits & Vegetables | D6: Sangha, Nagar and Varty | E6: 354.52
A7: 965755 | B7: Bananas | C7: Fruits & Vegetables | D7: Doshi, Sarraf and Sama | E7: 532.57
A8: 222892 | B8: Tomatoes | C8: Fruits & Vegetables | D8: Ramakrishnan-Ghose | E8: 869.22
A9: 516376 | B9: Onions | C9: Fruits & Vegetables | D9: Agarwal-Dhar | E9: 877.43
A10: 39154 | B10: Mangoes | C10: Fruits & Vegetables | D10: Suresh, Bose and Bajwa | E10: 946.86
A11: 34186 | B11: Mangoes | C11: Fruits & Vegetables | D11: Mandal-Kar | E11: 925.65
A12: 196719 | B12: Bananas | C12: Fruits & Vegetables | D12: Yogi Group | E12: 217.5
A13: 478531 | B13: Carrots | C13: Fruits & Vegetables | D13: Uppal Group | E13: 825.46
... A269: 114414 | B269: Vitamins | C269: Pharmacy | D269: Kara-Golla | E269: 832.06

Sheet customers
A1: customer_id | B1: registration_date | C1: customer_segment | D1: total_orders | E1: avg_order_value
A2: 97475543 | B2: 45059 | C2: Premium | D2: 13 | E2: 451.92
A3: 22077605 | B3: 45461 | C3: Inactive | D3: 4 | E3: 825.48
A4: 47822591 | B4: 45560 | C4: Regular | D4: 17 | E4: 1969.81
A5: 79726146 | B5: 45203 | C5: New | D5: 4 | E5: 220.09
A6: 57102800 | B6: 45373 | C6: Inactive | D6: 14 | E6: 578.14
A7: 54748429 | B7: 45404 | C7: New | D7: 2 | E7: 669.35
A8: 49152878 | B8: 45548 | C8: Premium | D8: 4 | E8: 973.62
A9: 16379942 | B9: 45392 | C9: Inactive | D9: 15 | E9: 1370.56
A10: 11071601 | B10: 45111 | C10: Inactive | D10: 17 | E10: 1950.54
A11: 68164013 | B11: 45106 | C11: New | D11: 1 | E11: 1061.82
A12: 80404839 | B12: 45029 | C12: Inactive | D12: 10 | E12: 1537.35
A13: 27038630 | B13: 45043 | C13: Regular | D13: 11 | E13: 1307.28
... A2484: 8241122 | B2484: 45565 | C2484: Inactive | D2484: 12 | E2484: 833.32
A2485: 97033691 | B2485: 45518 | C2485: Premium | D2485: 2 | E2485: 1268.05 | J2485: =COUNT(D2:D2501) -> 2500
A2486: 69242672 | B2486: 45035 | C2486: Regular | D2486: 3 | E2486: 1490.73
A2487: 41512861 | B2487: 45406 | C2487: Regular | D2487: 11 | E2487: 696.12
A2488: 3408982 | B2488: 45108 | C2488: Premium | D2488: 5 | E2488: 656.97
A2489: 42589311 | B2489: 45259 | C2489: Regular | D2489: 11 | E2489: 452.1
A2490: 75732571 | B2490: 45402 | C2490: New | D2490: 20 | E2490: 1981.72
A2491: 39681023 | B2491: 45173 | C2491: Premium | D2491: 16 | E2491: 1084.73
A2492: 94404245 | B2492: 45426 | C2492: Inactive | D2492: 5 | E2492: 564.03
A2493: 97484394 | B2493: 45387 | C2493: Inactive | D2493: 4 | E2493: 669.01
A2494: 66827191 | B2494: 45249 | C2494: New | D2494: 11 | E2494: 1808.42
A2495: 50554007 | B2495: 45020 | C2495: Premium | D2495: 5 | E2495: 1597.14
A2496: 65895091 | B2496: 45241 | C2496: Inactive | D2496: 8 | E2496: 1634.33
A2497: 48002829 | B2497: 45316 | C2497: Inactive | D2497: 17 | E2497: 754.33
... A2501: 78738569 | B2501: 45056 | C2501: Inactive | D2501: 4 | E2501: 376.5

Sheet master data
A1: order_id | B1: product_id | C1: quantity | D1: unit_price | E1: revenue | F1: product_name | G1: category | H1: brand | I1: order date | J1: customer id | K1: payment method | L1: customer segment
A2: 1961864118 | B2: 642612 | C2: 3 | D2: 517.03 | E2: =Table29[[#This Row],[quantity]]*Table29[[#This Row],[unit_price]] -> 1551.09 | F2: =_xlfn.XLOOKUP(Table29[[#This Row],[product_id]],products!A:A,products!B:B) -> Pet Treats | G2: =_xlfn.XLOOKUP(B:B,products!A:A,products!C:C) -> Pet Care | H2: =_xlfn.XLOOKUP(Table29[[#This Row],[product_id]],products!A:A,products!D:D) -> Pillay-Ahuja | I2: =_xlfn.XLOOKUP(Table29[[#This Row],[order_id]],orders!A:A,orders!C:C) -> 45490.357 | J2: =_xlfn.XLOOKUP(Table29[[#This Row],[order_id]],orders!A:A,orders!B:B) -> 30065862 | K2: =_xlfn.XLOOKUP(Table29[[#This Row],[order_id]],orders!A:A,orders!E:E) -> Cash | L2: =_xlfn.XLOOKUP(Table29[[#This Row],[customer id]],customers!A:A,customers!C:C) -> Regular
A3: 1549769649 | B3: 378676 | C3: 1 | D3: 881.42 | E3: =Table29[[#This Row],[quantity]]*Table29[[#This Row],[unit_price]] -> 881.42 | F3: =_xlfn.XLOOKUP(Table29[[#This Row],[product_id]],products!A:A,products!B:B) -> Orange Juice | G3: =_xlfn.XLOOKUP(B:B,products!A:A,products!C:C) -> Cold Drinks & Juices | H3: =_xlfn.XLOOKUP(Table29[[#This Row],[product_id]],products!A:A,products!D:D) -> Baral-Kamdar | I3: =_xlfn.XLOOKUP(Table29[[#This Row],[order_id]],orders!A:A,orders!C:C) -> 45440.551 | J3: =_xlfn.XLOOKUP(Table29[[#This Row],[order_id]],orders!A:A,orders!B:B) -> 9573071 | K3: =_xlfn.XLOOKUP(Table29[[#This Row],[order_id]],orders!A:A,orders!E:E) -> Cash | L3: =_xlfn.XLOOKUP(Table29[[#This Row],[customer id]],customers!A:A,customers!C:C) -> New
A4: 9185164487 | B4: 741341 | C4: 2 | D4: 923.84 | E4: =Table29[[#This Row],[quantity]]*Table29[[#This Row],[unit_price]] -> 1847.68 | F4: =_xlfn.XLOOKUP(Table29[[#This Row],[product_id]],products!A:A,products!B:B) -> Eggs | G4: =_xlfn.XLOOKUP(B:B,products!A:A,products!C:C) -> Dairy & Breakfast | H4: =_xlfn.XLOOKUP(Table29[[#This Row],[product_id]],products!A:A,products!D:D) -> Prasad LLC | I4: =_xlfn.XLOOKUP(Table29[[#This Row],[order_id]],orders!A:A,orders!C:C) -> 45558.547 | J4: =_xlfn.XLOOKUP(Table29[[#This Row],[order_id]],orders!A:A,orders!B:B) -> 45477575 | K4: =_xlfn.XLOOKUP(Table29[[#This Row],[order_id]],orders!A:A,orders!E:E) -> UPI | L4: =_xlfn.XLOOKUP(Table29[[#This Row],[customer id]],customers!A:A,customers!C:C) -> Inactive
A5: 9644738826 | B5: 561860 | C5: 1 | D5: 874.78 | E5: =Table29[[#This Row],[quantity]]*Table29[[#This Row],[unit_price]] -> 874.78 | F5: =_xlfn.XLOOKUP(Table29[[#This Row],[product_id]],products!A:A,products!B:B) -> Orange Juice | G5: =_xlfn.XLOOKUP(B:B,products!A:A,products!C:C) -> Cold Drinks & Juices | H5: =_xlfn.XLOOKUP(Table29[[#This Row],[product_id]],products!A:A,products!D:D) -> Gupta Ltd | I5: =_xlfn.XLOOKUP(Table29[[#This Row],[order_id]],orders!A:A,orders!C:C) -> 45254.678 | J5: =_xlfn.XLOOKUP(Table29[[#This Row],[order_id]],orders!A:A,orders!B:B) -> 88067569 | K5: =_xlfn.XLOOKUP(Table29[[#This Row],[order_id]],orders!A:A,orders!E:E) -> Card | L5: =_xlfn.XLOOKUP(Table29[[#This Row],[customer id]],customers!A:A,customers!C:C) -> Premium
A6: 5427684290 | B6: 602241 | C6: 2 | D6: 976.55 | E6: =Table29[[#This Row],[quantity]]*Table29[[#This Row],[unit_price]] -> 1953.1 | F6: =_xlfn.XLOOKUP(Table29[[#This Row],[product_id]],products!A:A,products!B:B) -> Nuts | G6: =_xlfn.XLOOKUP(B:B,products!A:A,products!C:C) -> Snacks & Munchies | H6: =_xlfn.XLOOKUP(Table29[[#This Row],[product_id]],products!A:A,products!D:D) -> Bahl-Pau | I6: =_xlfn.XLOOKUP(Table29[[#This Row],[order_id]],orders!A:A,orders!C:C) -> 45250.208 | J6: =_xlfn.XLOOKUP(Table29[[#This Row],[order_id]],orders!A:A,orders!B:B) -> 83298567 | K6: =_xlfn.XLOOKUP(Table29[[#This Row],[order_id]],orders!A:A,orders!E:E) -> Cash | L6: =_xlfn.XLOOKUP(Table29[[#This Row],[customer id]],customers!A:A,customers!C:C) -> Premium
A7: 3265154092 | B7: 681063 | C7: 1 | D7: 321.28 | E7: =Table29[[#This Row],[quantity]]*Table29[[#This Row],[unit_price]] -> 321.28 | F7: =_xlfn.XLOOKUP(Table29[[#This Row],[product_id]],products!A:A,products!B:B) -> Mango Drink | G7: =_xlfn.XLOOKUP(B:B,products!A:A,products!C:C) -> Cold Drinks & Juices | H7: =_xlfn.XLOOKUP(Table29[[#This Row],[product_id]],products!A:A,products!D:D) -> Dass and Sons | I7: =_xlfn.XLOOKUP(Table29[[#This Row],[order_id]],orders!A:A,orders!C:C) -> 45003.687 | J7: =_xlfn.XLOOKUP(Table29[[#This Row],[order_id]],orders!A:A,orders!B:B) -> 43367112 | K7: =_xlfn.XLOOKUP(Table29[[#This Row],[order_id]],orders!A:A,orders!E:E) -> UPI | L7: =_xlfn.XLOOKUP(Table29[[#This Row],[customer id]],customers!A:A,customers!C:C) -> New
A8: 4898355547 | B8: 56589 | C8: 3 | D8: 517.77 | E8: =Table29[[#This Row],[quantity]]*Table29[[#This Row],[unit_price]] -> 1553.31 | F8: =_xlfn.XLOOKUP(Table29[[#This Row],[product_id]],products!A:A,products!B:B) -> Vitamins | G8: =_xlfn.XLOOKUP(B:B,products!A:A,products!C:C) -> Pharmacy | H8: =_xlfn.XLOOKUP(Table29[[#This Row],[product_id]],products!A:A,products!D:D) -> Pai, Kashyap and Ramachandran | I8: =_xlfn.XLOOKUP(Table29[[#This Row],[order_id]],orders!A:A,orders!C:C) -> 45032.785 | J8: =_xlfn.XLOOKUP(Table29[[#This Row],[order_id]],orders!A:A,orders!B:B) -> 13284996 | K8: =_xlfn.XLOOKUP(Table29[[#This Row],[order_id]],orders!A:A,orders!E:E) -> Card | L8: =_xlfn.XLOOKUP(Table29[[#This Row],[customer id]],customers!A:A,customers!C:C) -> Regular
A9: 6568151549 | B9: 500739 | C9: 2 | D9: 359.98 | E9: =Table29[[#This Row],[quantity]]*Table29[[#This Row],[unit_price]] -> 719.96 | F9: =_xlfn.XLOOKUP(Table29[[#This Row],[product_id]],products!A:A,products!B:B) -> Bread | G9: =_xlfn.XLOOKUP(B:B,products!A:A,products!C:C) -> Dairy & Breakfast | H9: =_xlfn.XLOOKUP(Table29[[#This Row],[product_id]],products!A:A,products!D:D) -> Aggarwal Group | I9: =_xlfn.XLOOKUP(Table29[[#This Row],[order_id]],orders!A:A,orders!C:C) -> 45382.268 | J9: =_xlfn.XLOOKUP(Table29[[#This Row],[order_id]],orders!A:A,orders!B:B) -> 88866835 | K9: =_xlfn.XLOOKUP(Table29[[#This Row],[order_id]],orders!A:A,orders!E:E) -> Cash | L9: =_xlfn.XLOOKUP(Table29[[#This Row],[customer id]],customers!A:A,customers!C:C) -> Premium
A10: 6006693867 | B10: 490939 | C10: 1 | D10: 80.25 | E10: =Table29[[#This Row],[quantity]]*Table29[[#This Row],[unit_price]] -> 80.25 | F10: =_xlfn.XLOOKUP(Table29[[#This Row],[product_id]],products!A:A,products!B:B) -> Lotion | G10: =_xlfn.XLOOKUP(B:B,products!A:A,products!C:C) -> Personal Care | H10: =_xlfn.XLOOKUP(Table29[[#This Row],[product_id]],products!A:A,products!D:D) -> Roy, Barad and De | I10: =_xlfn.XLOOKUP(Table29[[#This Row],[order_id]],orders!A:A,orders!C:C) -> 45120.992 | J10: =_xlfn.XLOOKUP(Table29[[#This Row],[order_id]],orders!A:A,orders!B:B) -> 24496983 | K10: =_xlfn.XLOOKUP(Table29[[#This Row],[order_id]],orders!A:A,orders!E:E) -> Card | L10: =_xlfn.XLOOKUP(Table29[[#This Row],[customer id]],customers!A:A,customers!C:C) -> Regular
A11: 374186990 | B11: 760828 | C11: 2 | D11: 563.45 | E11: =Table29[[#This Row],[quantity]]*Table29[[#This Row],[unit_price]] -> 1126.9 | F11: =_xlfn.XLOOKUP(Table29[[#This Row],[product_id]],products!A:A,products!B:B) -> Pet Treats | G11: =_xlfn.XLOOKUP(B:B,products!A:A,products!C:C) -> Pet Care | H11: =_xlfn.XLOOKUP(Table29[[#This Row],[product_id]],products!A:A,products!D:D) -> Khurana, Khosla and Yohannan | I11: =_xlfn.XLOOKUP(Table29[[#This Row],[order_id]],orders!A:A,orders!C:C) -> 45147.053 | J11: =_xlfn.XLOOKUP(Table29[[#This Row],[order_id]],orders!A:A,orders!B:B) -> 52215833 | K11: =_xlfn.XLOOKUP(Table29[[#This Row],[order_id]],orders!A:A,orders!E:E) -> Wallet | L11: =_xlfn.XLOOKUP(Table29[[#This Row],[customer id]],customers!A:A,customers!C:C) -> Regular
A12: 4455336265 | B12: 753354 | C12: 3 | D12: 423.56 | E12: =Table29[[#This Row],[quantity]]*Table29[[#This Row],[unit_price]] -> 1270.68 | F12: =_xlfn.XLOOKUP(Table29[[#This Row],[product_id]],products!A:A,products!B:B) -> Shampoo | G12: =_xlfn.XLOOKUP(B:B,products!A:A,products!C:C) -> Personal Care | H12: =_xlfn.XLOOKUP(Table29[[#This Row],[product_id]],products!A:A,products!D:D) -> Sant-Mahajan | I12: =_xlfn.XLOOKUP(Table29[[#This Row],[order_id]],orders!A:A,orders!C:C) -> 45168.817 | J12: =_xlfn.XLOOKUP(Table29[[#This Row],[order_id]],orders!A:A,orders!B:B) -> 43431724 | K12: =_xlfn.XLOOKUP(Table29[[#This Row],[order_id]],orders!A:A,orders!E:E) -> UPI | L12: =_xlfn.XLOOKUP(Table29[[#This Row],[customer id]],customers!A:A,customers!C:C) -> New
A13: 3539286337 | B13: 684939 | C13: 1 | D13: 727.95 | E13: =Table29[[#This Row],[quantity]]*Table29[[#This Row],[unit_price]] -> 727.95 | F13: =_xlfn.XLOOKUP(Table29[[#This Row],[product_id]],products!A:A,products!B:B) -> Lotion | G13: =_xlfn.XLOOKUP(B:B,products!A:A,products!C:C) -> Personal Care | H13: =_xlfn.XLOOKUP(Table29[[#This Row],[product_id]],products!A:A,products!D:D) -> Sibal, Bhatnagar and Rajan | I13: =_xlfn.XLOOKUP(Table29[[#This Row],[order_id]],orders!A:A,orders!C:C) -> 45041.856 | J13: =_xlfn.XLOOKUP(Table29[[#This Row],[order_id]],orders!A:A,orders!B:B) -> 77559557 | K13: =_xlfn.XLOOKUP(Table29[[#This Row],[order_id]],orders!A:A,orders!E:E) -> Wallet | L13: =_xlfn.XLOOKUP(Table29[[#This Row],[customer id]],customers!A:A,customers!C:C) -> New
... A5001: 2494813730 | B5001: 136533 | C5001: 1 | D5001: 826.21 | E5001: =Table29[[#This Row],[quantity]]*Table29[[#This Row],[unit_price]] -> 826.21 | F5001: =_xlfn.XLOOKUP(Table29[[#This Row],[product_id]],products!A:A,products!B:B) -> Eggs | G5001: =_xlfn.XLOOKUP(B:B,products!A:A,products!C:C) -> Dairy & Breakfast | H5001: =_xlfn.XLOOKUP(Table29[[#This Row],[product_id]],products!A:A,products!D:D) -> Raghavan, Magar and Shanker | I5001: =_xlfn.XLOOKUP(Table29[[#This Row],[order_id]],orders!A:A,orders!C:C) -> 45161.503 | J5001: =_xlfn.XLOOKUP(Table29[[#This Row],[order_id]],orders!A:A,orders!B:B) -> 28663279 | K5001: =_xlfn.XLOOKUP(Table29[[#This Row],[order_id]],orders!A:A,orders!E:E) -> Card | L5001: =_xlfn.XLOOKUP(Table29[[#This Row],[customer id]],customers!A:A,customers!C:C) -> Premium

Sheet pivot tables
A1: REVENUE TREND | D1: TOP PRODUCTS | K1: CATEGORY SALES | O1: CUSTOMER SEGMENT ANALYSIS
A3: Row Labels | B3: Sum of revenue | K3: Row Labels | L3: Sum of revenue
A4: Jan | B4: 273090.91 | D4: Row Labels | E4: Sum of revenue | K4: Baby Care | L4: 348227.18 | O4: Row Labels | P4: Sum of revenue
A5: Feb | B5: 260130.49 | D5: Baby Food | E5: 86161.66 | K5: Cold Drinks & Juices | L5: 392717.62 | O5: Inactive | P5: 1188807
A6: Mar | B6: 351651.43 | D6: Baby Wipes | E6: 79730.32 | K6: Dairy & Breakfast | L6: 639222.19 | O6: New | P6: 1154350.8
A7: Apr | B7: 464638.03 | D7: Cola | E7: 72045.3 | K7: Fruits & Vegetables | L7: 559053.08 | O7: Premium | P7: 1269991.7
A8: May | B8: 534441.98 | D8: Diapers | E8: 29410.14 | K8: Grocery & Staples | L8: 359937.82 | O8: Regular | P8: 1359265.9
A9: Jun | B9: 472830.41 | D9: Iced Tea | E9: 40123.26 | K9: Household Care | L9: 444244.25 | O9: Grand Total | P9: 4972415.4
A10: Jul | B10: 489428.94 | D10: Lemonade | E10: 5991.12 | K10: Instant & Frozen Food | L10: 307212.65
A11: Aug | B11: 554767.75 | D11: Mango Drink | E11: 29774.96 | K11: Personal Care | L11: 394894.61
A12: Sept | B12: 508610.15 | D12: Orange Juice | E12: 47218.53 | K12: Pet Care | L12: 539888.75
A13: Oct | B13: 519722.72 | D13: Grand Total | E13: 390455.29 | K13: Pharmacy | L13: 592368.57
A14: Nov | B14: 289474.24 | K14: Snacks & Munchies | L14: 394648.71
A15: Dec | B15: 253628.38 | K15: Grand Total | L15: 4972415.4
A16: Grand Total | B16: 4972415.4

Sheet dashboard
